README.rst
setup.py
spyne_delegate.egg-info/PKG-INFO
spyne_delegate.egg-info/SOURCES.txt
spyne_delegate.egg-info/dependency_links.txt
spyne_delegate.egg-info/namespace_packages.txt
spyne_delegate.egg-info/not-zip-safe
spyne_delegate.egg-info/requires.txt
spyne_delegate.egg-info/top_level.txt
spynedelegate/__init__.py
spynedelegate/meta.py