Metadata-Version: 1.1
Name: spyne-delegate
Version: 1.0.2
Summary: Extension for spyne so you can easy override services using delegate classes
Home-page: https://github.com/devopsconsulting/python-spynedelegate
Author: Lars van de Kerkhof, Martijn Jacobs
Author-email: lars@devopsconsulting.nl, martijn@devopsconsulting.nl
License: BSD
Keywords: spyne delegate
Platform: UNKNOWN
Classifier: Development Status :: 3 - Alpha
Classifier: Environment :: Web Environment
Classifier: License :: OSI Approved :: BSD License
Classifier: Operating System :: Unix
Classifier: Programming Language :: Python
Classifier: Programming Language :: Python :: 2
Classifier: Programming Language :: Python :: 2.7
Classifier: Programming Language :: Python :: 3
Classifier: Programming Language :: Python :: 3.5
Classifier: Topic :: Software Development :: Libraries :: Application Frameworks
